dervin/__init__.py
dervin/app.py
dervin-0.0.1.dist-info/METADATA
dervin-0.0.1.dist-info/WHEEL
dervin-0.0.1.dist-info/entry_points.txt
dervin-0.0.1.dist-info/RECORD
