Metadata-Version: 2.1
Name: dervin
Version: 0.0.1
Summary: Engine that implements strategies to mitigate the phase ordering problem
Author-email: João Rocha <rocha.jmiguel@gmail.com>
Requires-Python: >=3.7
